pyconvexity/__init__.py
pyconvexity/_version.py
pyconvexity/dashboard.py
pyconvexity/timeseries.py
pyconvexity/core/__init__.py
pyconvexity/core/database.py
pyconvexity/core/errors.py
pyconvexity/core/types.py
pyconvexity/data/README.md
pyconvexity/data/__init__.py
pyconvexity/data/loaders/__init__.py
pyconvexity/data/loaders/cache.py
pyconvexity/data/schema/01_core_schema.sql
pyconvexity/data/schema/02_data_metadata.sql
pyconvexity/data/schema/03_validation_data.sql
pyconvexity/data/sources/__init__.py
pyconvexity/data/sources/gem.py
pyconvexity/io/__init__.py
pyconvexity/io/excel_exporter.py
pyconvexity/io/excel_importer.py
pyconvexity/io/netcdf_exporter.py
pyconvexity/io/netcdf_importer.py
pyconvexity/models/__init__.py
pyconvexity/models/attributes.py
pyconvexity/models/carriers.py
pyconvexity/models/components.py
pyconvexity/models/network.py
pyconvexity/models/results.py
pyconvexity/models/scenarios.py
pyconvexity/solvers/__init__.py
pyconvexity/solvers/pypsa/__init__.py
pyconvexity/solvers/pypsa/api.py
pyconvexity/solvers/pypsa/batch_loader.py
pyconvexity/solvers/pypsa/builder.py
pyconvexity/solvers/pypsa/clearing_price.py
pyconvexity/solvers/pypsa/constraints.py
pyconvexity/solvers/pypsa/solver.py
pyconvexity/solvers/pypsa/storage.py
pyconvexity/transformations/__init__.py
pyconvexity/transformations/api.py
pyconvexity/transformations/time_axis.py
pyconvexity/validation/__init__.py
pyconvexity/validation/rules.py
pyconvexity-0.5.1.post1.dist-info/METADATA
pyconvexity-0.5.1.post1.dist-info/WHEEL
pyconvexity-0.5.1.post1.dist-info/top_level.txt
pyconvexity-0.5.1.post1.dist-info/RECORD
