Metadata-Version: 2.4
Name: pyconvexity
Version: 0.5.1.post1
Summary: Python library for energy system modeling and optimization with PyPSA
Author-email: Convexity Team <info@convexity.com>
License: MIT
Project-URL: Homepage, https://github.com/bayesian-energy/pyconvexity
Project-URL: Repository, https://github.com/bayesian-energy/pyconvexity
Project-URL: Issues, https://github.com/bayesian-energy/pyconvexity/issues
Project-URL: Documentation, https://pyconvexity.readthedocs.io
Classifier: Development Status :: 3 - Alpha
Classifier: Intended Audience :: Science/Research
Classifier: License :: OSI Approved :: MIT License
Classifier: Programming Language :: Python :: 3
Classifier: Programming Language :: Python :: 3.9
Classifier: Programming Language :: Python :: 3.10
Classifier: Programming Language :: Python :: 3.11
Classifier: Programming Language :: Python :: 3.12
Classifier: Topic :: Scientific/Engineering
Requires-Python: >=3.9
Requires-Dist: pandas>=1.5.0
Requires-Dist: numpy>=1.21.0
Requires-Dist: pyarrow>=10.0.0
Provides-Extra: pypsa
Requires-Dist: pypsa>=0.25.0; extra == "pypsa"
Requires-Dist: networkx; extra == "pypsa"
Requires-Dist: scipy; extra == "pypsa"
Requires-Dist: xarray; extra == "pypsa"
Provides-Extra: excel
Requires-Dist: openpyxl>=3.0.0; extra == "excel"
Requires-Dist: xlsxwriter>=3.0.0; extra == "excel"
Provides-Extra: netcdf
Requires-Dist: netcdf4>=1.6.0; extra == "netcdf"
Requires-Dist: xarray>=2022.3.0; extra == "netcdf"
Provides-Extra: data
Requires-Dist: country-converter>=1.0.0; extra == "data"
Requires-Dist: pyyaml>=6.0.0; extra == "data"
Provides-Extra: dev
Requires-Dist: pytest>=7.0.0; extra == "dev"
Requires-Dist: pytest-cov>=4.0.0; extra == "dev"
Requires-Dist: black>=22.0.0; extra == "dev"
Requires-Dist: isort>=5.10.0; extra == "dev"
Requires-Dist: mypy>=1.0.0; extra == "dev"
Requires-Dist: pre-commit>=2.20.0; extra == "dev"
Provides-Extra: all
Requires-Dist: pyconvexity[data,excel,netcdf,pypsa]; extra == "all"
